GreenDIRAC/__init__.py
GreenDIRAC/WorkloadManagementSystem/__init__.py
GreenDIRAC/WorkloadManagementSystem/Agent/GreenReportingAgent.py
GreenDIRAC/WorkloadManagementSystem/Agent/__init__.py
greendirac-0.0.0a2.dist-info/METADATA
greendirac-0.0.0a2.dist-info/WHEEL
greendirac-0.0.0a2.dist-info/top_level.txt
greendirac-0.0.0a2.dist-info/RECORD
