Metadata-Version: 2.4
Name: greendirac
Version: 0.0.0a2
Summary: GreenDIRAC is a DIRAC extension for the GreenDIGIT project
Home-page: https://github.com/GreenDIGIT-project/GreenDIRAC
Author: GreenDIRAC
Author-email: atsareg@in2p3.fr
License: GPLv3
Requires-Python: >=3.11
